LICENSE.txt
MANIFEST.in
README.rst
pyproject.toml
setup.py
rbf/__init__.py
rbf/_version.py
rbf/basis.py
rbf/gauss.py
rbf/gproc.py
rbf/interpolate.py
rbf/linalg.py
rbf/poly.c
rbf/sputils.c
rbf/utils.py
rbf/_rbf_ufuncs/make_rbf_ufuncs.py
rbf/_rbf_ufuncs/metadata.json
rbf/_rbf_ufuncs/wrapped_code_0.c
rbf/_rbf_ufuncs/wrapped_code_0.h
rbf/_rbf_ufuncs/wrapped_code_1.c
rbf/_rbf_ufuncs/wrapped_code_1.h
rbf/_rbf_ufuncs/wrapped_code_10.c
rbf/_rbf_ufuncs/wrapped_code_10.h
rbf/_rbf_ufuncs/wrapped_code_11.c
rbf/_rbf_ufuncs/wrapped_code_11.h
rbf/_rbf_ufuncs/wrapped_code_12.c
rbf/_rbf_ufuncs/wrapped_code_12.h
rbf/_rbf_ufuncs/wrapped_code_13.c
rbf/_rbf_ufuncs/wrapped_code_13.h
rbf/_rbf_ufuncs/wrapped_code_14.c
rbf/_rbf_ufuncs/wrapped_code_14.h
rbf/_rbf_ufuncs/wrapped_code_15.c
rbf/_rbf_ufuncs/wrapped_code_15.h
rbf/_rbf_ufuncs/wrapped_code_16.c
rbf/_rbf_ufuncs/wrapped_code_16.h
rbf/_rbf_ufuncs/wrapped_code_17.c
rbf/_rbf_ufuncs/wrapped_code_17.h
rbf/_rbf_ufuncs/wrapped_code_18.c
rbf/_rbf_ufuncs/wrapped_code_18.h
rbf/_rbf_ufuncs/wrapped_code_19.c
rbf/_rbf_ufuncs/wrapped_code_19.h
rbf/_rbf_ufuncs/wrapped_code_2.c
rbf/_rbf_ufuncs/wrapped_code_2.h
rbf/_rbf_ufuncs/wrapped_code_20.c
rbf/_rbf_ufuncs/wrapped_code_20.h
rbf/_rbf_ufuncs/wrapped_code_21.c
rbf/_rbf_ufuncs/wrapped_code_21.h
rbf/_rbf_ufuncs/wrapped_code_22.c
rbf/_rbf_ufuncs/wrapped_code_22.h
rbf/_rbf_ufuncs/wrapped_code_23.c
rbf/_rbf_ufuncs/wrapped_code_23.h
rbf/_rbf_ufuncs/wrapped_code_24.c
rbf/_rbf_ufuncs/wrapped_code_24.h
rbf/_rbf_ufuncs/wrapped_code_25.c
rbf/_rbf_ufuncs/wrapped_code_25.h
rbf/_rbf_ufuncs/wrapped_code_26.c
rbf/_rbf_ufuncs/wrapped_code_26.h
rbf/_rbf_ufuncs/wrapped_code_27.c
rbf/_rbf_ufuncs/wrapped_code_27.h
rbf/_rbf_ufuncs/wrapped_code_28.c
rbf/_rbf_ufuncs/wrapped_code_28.h
rbf/_rbf_ufuncs/wrapped_code_29.c
rbf/_rbf_ufuncs/wrapped_code_29.h
rbf/_rbf_ufuncs/wrapped_code_3.c
rbf/_rbf_ufuncs/wrapped_code_3.h
rbf/_rbf_ufuncs/wrapped_code_30.c
rbf/_rbf_ufuncs/wrapped_code_30.h
rbf/_rbf_ufuncs/wrapped_code_31.c
treverhines_rbf.egg-info/PKG-INFO
treverhines_rbf.egg-info/SOURCES.txt
treverhines_rbf.egg-info/dependency_links.txt
treverhines_rbf.egg-info/requires.txt
treverhines_rbf.egg-info/top_level.txt