Metadata-Version: 2.1
Name: treverhines-rbf
Version: 2025.7.4.1
Summary: Package containing the tools necessary for radial basis function (RBF) applications
Home-page: https://www.github.com/treverhines/RBF
Author: Trever Hines
Author-email: treverhines@gmail.com
License: MIT
Requires-Python: >=3.5
License-File: LICENSE.txt
Requires-Dist: numpy>=1.10
Requires-Dist: scipy
Requires-Dist: sympy
Requires-Dist: cython
Requires-Dist: rtree
